{
    "dolmen": {
        "branch": "5e22e653ec376336bbbed50aca4946db8edbc90f",
        "description": "Dolmen provides a library and a binary to parse, typecheck, and evaluate languages used in automated deduction",
        "homepage": "",
        "owner": "Gbury",
        "repo": "dolmen",
        "rev": "5e22e653ec376336bbbed50aca4946db8edbc90f",
        "sha256": "1wmmq3x8zcp2zh3xpchjvhyj85qbydrpd2cf9awn4nxxaqi06yjn",
        "type": "tarball",
        "url": "https://github.com/Gbury/dolmen/archive/5e22e653ec376336bbbed50aca4946db8edbc90f.tar.gz",
        "url_template": "https://github.com/<owner>/<repo>/archive/<rev>.tar.gz",
        "version": "dev"
    },
    "nixpkgs": {
        "branch": "release-23.11",
        "description": "Nix Packages collection",
        "homepage": null,
        "owner": "NixOS",
        "repo": "nixpkgs",
        "rev": "544b36d1b4815fd5f187ed00ff7a59fd0323317c",
        "sha256": "0jh67yjfkv9sj4xldlv9p6whljg0rh96hy7x082061ghsb3kg6q4",
        "type": "tarball",
        "url": "https://github.com/NixOS/nixpkgs/archive/544b36d1b4815fd5f187ed00ff7a59fd0323317c.tar.gz",
        "url_template": "https://github.com/<owner>/<repo>/archive/<rev>.tar.gz"
    },
    "ocplib-simplex": {
        "branch": "v0.5",
        "description": "A library implementing a simplex algorithm, in a functional style, for solving systems of linear inequalities",
        "homepage": "",
        "owner": "OCamlPro",
        "repo": "ocplib-simplex",
        "rev": "9b0944c81088b9039775e48cdbc3499128ca3692",
        "sha256": "1dxx68k2smnxrp9b8snpvi74d41yfxn2j6swbqnny6r1d1950bmk",
        "type": "tarball",
        "url": "https://github.com/OCamlPro/ocplib-simplex/archive/9b0944c81088b9039775e48cdbc3499128ca3692.tar.gz",
        "url_template": "https://github.com/<owner>/<repo>/archive/<rev>.tar.gz",
        "version": "0.5"
    },
    "pp_loc": {
        "branch": "v2.1.0",
        "description": "Pretty-printing for error source locations",
        "homepage": "https://armael.github.io/pp_loc/pp_loc/",
        "owner": "Armael",
        "repo": "pp_loc",
        "rev": "d8162fd289849ea2f4125054ab88540416bdaa25",
        "sha256": "1wf5pqfxbfbjlwg24n3w99xm29qn1xjjjqn2z01vr5wgxcj9nfvd",
        "type": "tarball",
        "url": "https://github.com/Armael/pp_loc/archive/d8162fd289849ea2f4125054ab88540416bdaa25.tar.gz",
        "url_template": "https://github.com/<owner>/<repo>/archive/<rev>.tar.gz",
        "version": "2.1.0"
    }
}
